cli.py
logcfg.py
tallyman.py
tallyman-0.0.1.dist-info/METADATA
tallyman-0.0.1.dist-info/WHEEL
tallyman-0.0.1.dist-info/namespace_packages.txt
tallyman-0.0.1.dist-info/top_level.txt
tallyman-0.0.1.dist-info/zip-safe
tallyman-0.0.1.dist-info/RECORD
