Metadata-Version: 2.1
Name: tallyman
Version: 0.0.1
Summary: A simple tool to organize files
Home-page: https://github.com/HostenWang/tallyman
Author: HostenWang
Author-email: hostenwang@foxmail.com
Maintainer: 
Maintainer-email: 
Keywords: cli tool organize
Classifier: Development Status :: 3 - Alpha
Classifier: Intended Audience :: Developers
Classifier: License :: OSI Approved :: MIT License
Classifier: Operating System :: Microsoft
Classifier: Operating System :: Unix
Classifier: Programming Language :: Python :: 3
Classifier: Topic :: Utilities
Requires-Python: >=3.6
Requires-Dist: PyYAML (~=6.0)
Requires-Dist: click (~=8.1.3)
